cognite/transformations_cli/__init__.py
cognite/transformations_cli/__main__.py
cognite/transformations_cli/clients.py
cognite/transformations_cli/commands/__init__.py
cognite/transformations_cli/commands/base.py
cognite/transformations_cli/commands/delete.py
cognite/transformations_cli/commands/deploy/__init__.py
cognite/transformations_cli/commands/deploy/deploy.py
cognite/transformations_cli/commands/deploy/load_yaml.py
cognite/transformations_cli/commands/deploy/transformation_config.py
cognite/transformations_cli/commands/deploy/transformation_types.py
cognite/transformations_cli/commands/deploy/transformation_types_legacy.py
cognite/transformations_cli/commands/deploy/transformations_api.py
cognite/transformations_cli/commands/jobs.py
cognite/transformations_cli/commands/list.py
cognite/transformations_cli/commands/query.py
cognite/transformations_cli/commands/run.py
cognite/transformations_cli/commands/show.py
cognite/transformations_cli/commands/utils.py
cognite_transformations_cli-2.3.12.dist-info/LICENSE
cognite_transformations_cli-2.3.12.dist-info/METADATA
cognite_transformations_cli-2.3.12.dist-info/WHEEL
cognite_transformations_cli-2.3.12.dist-info/entry_points.txt
cognite_transformations_cli-2.3.12.dist-info/RECORD
