Metadata-Version: 2.1
Name: cognite-transformations-cli
Version: 2.3.12
Summary: A CLI for the Transformations service in CDF
Home-page: https://github.com/cognitedata/transformations-cli
License: Apache-2.0
Author: Mathias Lohne
Author-email: mathias.lohne@cognite.com
Requires-Python: >=3.8,<4.0
Classifier: License :: OSI Approved :: Apache Software License
Classifier: Programming Language :: Python :: 3
Classifier: Programming Language :: Python :: 3.8
Classifier: Programming Language :: Python :: 3.9
Classifier: Programming Language :: Python :: 3.10
Classifier: Programming Language :: Python :: 3.11
Classifier: Programming Language :: Python :: 3.12
Classifier: Programming Language :: Python :: 3.13
Requires-Dist: PyYAML (>=6.0,<7.0)
Requires-Dist: click (>=8.0.2,<9.0.0)
Requires-Dist: cognite-sdk (==6.39.6)
Requires-Dist: dacite (>=1.6.0,<2.0.0)
Requires-Dist: pyparsing (>=3.0.9,<4.0.0)
Requires-Dist: python-dotenv (>=1.0.0,<2.0.0)
Requires-Dist: regex (>=2023.0.0,<2024.0.0)
Requires-Dist: sqlparse (>=0.4.2,<0.6.0)
Requires-Dist: tabulate (>=0.9.0,<0.10.0)
Requires-Dist: types-retry (>=0.9.0,<0.10.0)
Requires-Dist: types-tabulate (>=0.8.3,<0.9.0)
Project-URL: Repository, https://github.com/cognitedata/transformations-cli
